README.md
setup.cfg
setup.py
metintos/__init__.py
metintos/constants.py
metintos/flow_tuning.py
metintos/io.py
metintos/isa.py
metintos/optiflow.py
metintos/utils.py
metintos.egg-info/PKG-INFO
metintos.egg-info/SOURCES.txt
metintos.egg-info/dependency_links.txt
metintos.egg-info/not-zip-safe
metintos.egg-info/requires.txt
metintos.egg-info/top_level.txt
test/test_dataset_handlers.py
test/test_dataset_no_ensemble.py
test/test_dataset_no_ensemble_no_vertical_var.py