Metadata-Version: 2.1
Name: metintos
Version: 0.2.3
Summary: Meteorological Interpolation Toolbox for Optimization and Simulation
Home-page: https://github.com/javiergarciaheras/mitos
Author: Daniel González Arribas
Author-email: dangonza@ing.uc3m.es
License: lgpl-3.0
Download-URL: https://github.com/javiergarciaheras/mitos/archive/v_01.tar.gz
Keywords: Optical flow,Meteorological,Interpolation,Optimization,Simulation
Platform: UNKNOWN
Classifier: Development Status :: 4 - Beta
Classifier: Intended Audience :: Science/Research
Classifier: Intended Audience :: Education
Classifier: Intended Audience :: Developers
Classifier: Topic :: Software Development :: Build Tools
Classifier: License :: OSI Approved :: GNU Lesser General Public License v3 (LGPLv3)
Classifier: Operating System :: MacOS :: MacOS X
Classifier: Operating System :: Microsoft :: Windows
Classifier: Operating System :: Unix
Classifier: Programming Language :: Python
Classifier: Programming Language :: Python :: 3
Classifier: Programming Language :: Python :: 3.5
Classifier: Programming Language :: Python :: 3.6
Classifier: Programming Language :: Python :: 3.7
Classifier: Programming Language :: Python :: 3.8
Provides-Extra: tuning
